Workbook

Sheet Membres
A1: GESTION DES MEMBRES
A3: ID | B3: Nom | C3: Prénom | D3: Téléphone | E3: Email | F3: Date d'inscription | G3: Date de naissance | H3: Médecine du sport
A4: M001 | B4: Nom1 | C4: Prénom1 | D4: 0639228299 | E4: membre1@email.com | F4: 45699.658 | G4: 29843.658 | H4: Non
A5: M002 | B5: Nom2 | C5: Prénom2 | D5: 0646650797 | E5: membre2@email.com | F5: 45652.658 | G5: 35880.658 | H5: Non
A6: M003 | B6: Nom3 | C6: Prénom3 | D6: 0698824930 | E6: membre3@email.com | F6: 45738.658 | G6: 37067.658 | H6: Oui
A7: M004 | B7: Nom4 | C7: Prénom4 | D7: 0695326398 | E7: membre4@email.com | F7: 45682.658 | G7: 27098.658 | H7: Non
A8: M005 | B8: Nom5 | C8: Prénom5 | D8: 0697252350 | E8: membre5@email.com | F8: 45690.658 | G8: 28185.658 | H8: Non
A9: M006 | B9: Nom6 | C9: Prénom6 | D9: 0611401238 | E9: membre6@email.com | F9: 45812.658 | G9: 32610.658 | H9: Non
A10: M007 | B10: Nom7 | C10: Prénom7 | D10: 0675072418 | E10: membre7@email.com | F10: 45712.658 | G10: 38908.658 | H10: Oui
A11: M008 | B11: Nom8 | C11: Prénom8 | D11: 0696472794 | E11: membre8@email.com | F11: 45959.658 | G11: 32634.658 | H11: Oui
A12: M009 | B12: Nom9 | C12: Prénom9 | D12: 0618875000 | E12: membre9@email.com | F12: 45761.658 | G12: 28658.658 | H12: Oui
A13: M010 | B13: Nom10 | C13: Prénom10 | D13: 0688340990 | E13: membre10@email.com | F13: 45634.658 | G13: 36031.658 | H13: Non
A14: M011 | B14: Nom11 | C14: Prénom11 | D14: 0615217084 | E14: membre11@email.com | F14: 45750.658 | G14: 27100.658 | H14: Non
A15: M012 | B15: Nom12 | C15: Prénom12 | D15: 0676457845 | E15: membre12@email.com | F15: 45758.658 | G15: 35997.658 | H15: Non
... A23: M020 | B23: Nom20 | C23: Prénom20 | D23: 0639832508 | E23: membre20@email.com | F23: 45883.658 | G23: 26872.658 | H23: Non

Sheet Abonnements
A1: GESTION DES ABONNEMENTS
A3: ID Abonnement | B3: ID Membre | C3: Type | D3: Date début | E3: Date fin | F3: Prix | G3: Statut | H3: Méthode de paiement
A4: A0001 | B4: M008 | C4: Mensuel | D4: 45973.658 | E4: 46003.658 | F4: 30 | G4: Expiré | H4: Virement
A5: A0002 | B5: M009 | C5: Annuel | D5: 45897.658 | E5: 46262.658 | F5: 300 | G5: Expiré | H5: Chèque
A6: A0003 | B6: M002 | C6: Annuel | D6: 45986.658 | E6: 46351.658 | F6: 300 | G6: Résilié | H6: Virement
A7: A0004 | B7: M008 | C7: Trimestriel | D7: 45864.658 | E7: 45954.658 | F7: 80 | G7: Résilié | H7: Virement
A8: A0005 | B8: M006 | C8: Trimestriel | D8: 45816.658 | E8: 45906.658 | F8: 80 | G8: Résilié | H8: Virement
A9: A0006 | B9: M008 | C9: Mensuel | D9: 45810.658 | E9: 45840.658 | F9: 30 | G9: Expiré | H9: Espèces
A10: A0007 | B10: M019 | C10: Mensuel | D10: 45698.658 | E10: 45728.658 | F10: 30 | G10: Actif | H10: Chèque
A11: A0008 | B11: M017 | C11: Annuel | D11: 45952.658 | E11: 46317.658 | F11: 300 | G11: Résilié | H11: Virement
A12: A0009 | B12: M014 | C12: Trimestriel | D12: 45834.658 | E12: 45924.658 | F12: 80 | G12: Expiré | H12: Virement
A13: A0010 | B13: M008 | C13: Trimestriel | D13: 45854.658 | E13: 45944.658 | F13: 80 | G13: Expiré | H13: Carte
A14: A0011 | B14: M014 | C14: Annuel | D14: 45959.658 | E14: 46324.658 | F14: 300 | G14: Expiré | H14: Virement
A15: A0012 | B15: M015 | C15: Mensuel | D15: 45959.658 | E15: 45989.658 | F15: 30 | G15: Actif | H15: Carte
... A23: A0020 | B23: M018 | C23: Annuel | D23: 45977.658 | E23: 46342.658 | F23: 300 | G23: Résilié | H23: Chèque

Sheet Paiements
A1: SUIVI DES PAIEMENTS
A3: ID Paiement | B3: ID Membre | C3: Date | D3: Montant | E3: Méthode | F3: Statut
A4: P00001 | B4: M015 | C4: 45906.658 | D4: 85 | E4: Espèces | F4: Payé
A5: P00002 | B5: M019 | C5: 45781.658 | D5: 80 | E5: Chèque | F5: Payé
A6: P00003 | B6: M017 | C6: 45659.658 | D6: 85 | E6: Chèque | F6: Payé
A7: P00004 | B7: M018 | C7: 45709.658 | D7: 85 | E7: Carte | F7: Payé
A8: P00005 | B8: M001 | C8: 45751.658 | D8: 80 | E8: Carte | F8: Payé
A9: P00006 | B9: M010 | C9: 45924.658 | D9: 300 | E9: Espèces | F9: Payé
A10: P00007 | B10: M003 | C10: 45861.658 | D10: 35 | E10: Chèque | F10: Payé
A11: P00008 | B11: M002 | C11: 45745.658 | D11: 310 | E11: Espèces | F11: Payé
A12: P00009 | B12: M014 | C12: 45845.658 | D12: 35 | E12: Espèces | F12: Payé
A13: P00010 | B13: M013 | C13: 45977.658 | D13: 30 | E13: Espèces | F13: Payé
A14: P00011 | B14: M012 | C14: 45877.658 | D14: 310 | E14: Chèque | F14: Payé
A15: P00012 | B15: M005 | C15: 45875.658 | D15: 35 | E15: Carte | F15: Payé
... A53: P00050 | B53: M010 | C53: 45839.658 | D53: 300 | E53: Chèque | F53: Payé

Sheet Présences
A1: SUIVI DES PRÉSENCES
A3: ID Séance | B3: ID Membre | C3: Date | D3: Heure d'arrivée | E3: Heure de départ | F3: Durée (min) | G3: Activité
A4: S00001 | B4: M014 | C4: 45993.658 | D4: 45993.729 | E4: 45993.79 | F4: =HOUR(E4-D4)*60 + MINUTE(E4-D4) -> 88 | G4: Cours collectif
A5: S00002 | B5: M004 | C5: 45987.658 | D5: 45987.727 | E5: 45987.769 | F5: =HOUR(E5-D5)*60 + MINUTE(E5-D5) -> 60 | G5: Musculation
A6: S00003 | B6: M006 | C6: 45988.658 | D6: 45988.338 | E6: 45988.391 | F6: =HOUR(E6-D6)*60 + MINUTE(E6-D6) -> 77 | G6: Cours collectif
A7: S00004 | B7: M004 | C7: 45977.658 | D7: 45977.653 | E7: 45977.685 | F7: =HOUR(E7-D7)*60 + MINUTE(E7-D7) -> 47 | G7: Étirement
A8: S00005 | B8: M004 | C8: 45972.658 | D8: 45972.417 | E8: 45972.44 | F8: =HOUR(E8-D8)*60 + MINUTE(E8-D8) -> 32 | G8: Musculation
A9: S00006 | B9: M004 | C9: 45986.658 | D9: 45986.641 | E9: 45986.692 | F9: =HOUR(E9-D9)*60 + MINUTE(E9-D9) -> 74 | G9: Musculation
A10: S00007 | B10: M018 | C10: 45975.658 | D10: 45975.835 | E10: 45975.868 | F10: =HOUR(E10-D10)*60 + MINUTE(E10-D10) -> 47 | G10: Étirement
A11: S00008 | B11: M015 | C11: 45984.658 | D11: 45984.425 | E11: 45984.461 | F11: =HOUR(E11-D11)*60 + MINUTE(E11-D11) -> 52 | G11: Étirement
A12: S00009 | B12: M013 | C12: 45989.658 | D12: 45989.63 | E12: 45989.674 | F12: =HOUR(E12-D12)*60 + MINUTE(E12-D12) -> 64 | G12: Cardio
A13: S00010 | B13: M002 | C13: 45971.658 | D13: 45971.631 | E13: 45971.703 | F13: =HOUR(E13-D13)*60 + MINUTE(E13-D13) -> 103 | G13: Étirement
A14: S00011 | B14: M007 | C14: 45996.658 | D14: 45996.547 | E14: 45996.592 | F14: =HOUR(E14-D14)*60 + MINUTE(E14-D14) -> 65 | G14: Musculation
A15: S00012 | B15: M016 | C15: 45992.658 | D15: 45992.777 | E15: 45992.801 | F15: =HOUR(E15-D15)*60 + MINUTE(E15-D15) -> 35 | G15: Cours collectif
... A103: S00100 | B103: M013 | C103: 45991.658 | D103: 45991.773 | E103: 45991.814 | F103: =HOUR(E103-D103)*60 + MINUTE(E103-D103) -> 59 | G103: Cardio

Sheet Tableau de Bord
A1: TABLEAU DE BORD ISBISPORTCLUB
A2: Données au 08/12/2025
A5: Membres actifs | B5: =COUNTIF(Membres!H:H,"Oui") -> 8
A6: Abonnements actifs | B6: =COUNTIF(Abonnements!G:G,"Actif") -> 3
A7: Recettes mensuelles | B7: =SUMIFS(Paiements!D:D,Paiements!C:C,">="&EOMONTH(TODAY(),-1)+1,Paiements!C:C,"<="&EOMONTH(TODAY(),0)) -> 0
A8: Taux de fréquentation | B8: =COUNT(Présences!A:A)/MAX(1,COUNT(Membres!A:A))/30 -> 0
A10: Répartition des abonnements par type
A12: Type d'abonnement | B12: Nombre
A13: Mensuel | B13: =COUNTIF(Abonnements!C:C,"Mensuel") -> 7
A14: Trimestriel | B14: =COUNTIF(Abonnements!C:C,"Trimestriel") -> 5
A15: Annuel | B15: =COUNTIF(Abonnements!C:C,"Annuel") -> 8
A25: Recettes mensuelles (12 derniers mois)
A27: Mois | B27: Montant
A28: 12/2025 | B28: =SOMMEPROD((MOIS(Paiements!C$4:C$1000)=12)*(ANNEE(Paiements!C$4:C$1000)=2025)*Paiements!D$4:D$1000) -> #NAME?
A29: 11/2025 | B29: =SOMMEPROD((MOIS(Paiements!C$4:C$1000)=11)*(ANNEE(Paiements!C$4:C$1000)=2025)*Paiements!D$4:D$1000) -> #NAME?
A30: 10/2025 | B30: =SOMMEPROD((MOIS(Paiements!C$4:C$1000)=10)*(ANNEE(Paiements!C$4:C$1000)=2025)*Paiements!D$4:D$1000) -> #NAME?
A31: 09/2025 | B31: =SOMMEPROD((MOIS(Paiements!C$4:C$1000)=9)*(ANNEE(Paiements!C$4:C$1000)=2025)*Paiements!D$4:D$1000) -> #NAME?
A32: 08/2025 | B32: =SOMMEPROD((MOIS(Paiements!C$4:C$1000)=8)*(ANNEE(Paiements!C$4:C$1000)=2025)*Paiements!D$4:D$1000) -> #NAME?
A33: 07/2025 | B33: =SOMMEPROD((MOIS(Paiements!C$4:C$1000)=7)*(ANNEE(Paiements!C$4:C$1000)=2025)*Paiements!D$4:D$1000) -> #NAME?
A34: 06/2025 | B34: =SOMMEPROD((MOIS(Paiements!C$4:C$1000)=6)*(ANNEE(Paiements!C$4:C$1000)=2025)*Paiements!D$4:D$1000) -> #NAME?
A35: 05/2025 | B35: =SOMMEPROD((MOIS(Paiements!C$4:C$1000)=5)*(ANNEE(Paiements!C$4:C$1000)=2025)*Paiements!D$4:D$1000) -> #NAME?
A36: 04/2025 | B36: =SOMMEPROD((MOIS(Paiements!C$4:C$1000)=4)*(ANNEE(Paiements!C$4:C$1000)=2025)*Paiements!D$4:D$1000) -> #NAME?
A37: 03/2025 | B37: =SOMMEPROD((MOIS(Paiements!C$4:C$1000)=3)*(ANNEE(Paiements!C$4:C$1000)=2025)*Paiements!D$4:D$1000) -> #NAME?
A38: 02/2025 | B38: =SOMMEPROD((MOIS(Paiements!C$4:C$1000)=2)*(ANNEE(Paiements!C$4:C$1000)=2025)*Paiements!D$4:D$1000) -> #NAME?
A39: 01/2025 | B39: =SOMMEPROD((MOIS(Paiements!C$4:C$1000)=1)*(ANNEE(Paiements!C$4:C$1000)=2025)*Paiements!D$4:D$1000) -> #NAME?
